[
  {
    "subjectCode": "KCS401",
    "academicYear": "2022-23",
    "year": 2023,
    "examType": "EVEN_SEM",
    "rawText": "Define two main functions of an operating system.",
    "marks": 2,
    "markType": "TWO",
    "section": "A",
    "qNo": "1a",
    "unitId": "OS-U1",
    "topicId": "OS-U1-INTRO",
    "subTopicId": "OS-U1-INTRO-FUNC",
    "canonicalTopicName": "OS Functions and Structure",
    "canonicalSubTopicName": "Operating System Functions",
    "questionType": "DEFINE",
    "hasDiagram": false,
    "difficulty": "EASY",
    "mappingStatus": "MAPPED",
    "mappingConfidence": "HIGH",
    "isRepeat": true,
    "repeatYears": [2018, 2019, 2022]
  },
  {
    "subjectCode": "KCS401",
    "academicYear": "2022-23",
    "year": 2023,
    "examType": "EVEN_SEM",
    "rawText": "Explain the principal advantages of multiprogramming.",
    "marks": 2,
    "markType": "TWO",
    "section": "A",
    "qNo": "1b",
    "unitId": "OS-U1",
    "topicId": "OS-U1-CLASSIFY",
    "subTopicId": "OS-U1-CLASSIFY-MULTI",
    "canonicalTopicName": "Classification of Operating Systems",
    "canonicalSubTopicName": "Multiprocessor and Multithreaded Systems",
    "questionType": "EXPLAIN",
    "hasDiagram": false,
    "difficulty": "EASY",
    "mappingStatus": "MAPPED",
    "mappingConfidence": "HIGH",
    "isRepeat": false,
    "repeatYears": []
  },
  {
    "subjectCode": "KCS401",
    "academicYear": "2022-23",
    "year": 2023,
    "examType": "EVEN_SEM",
    "rawText": "Define the term busy waiting.",
    "marks": 2,
    "markType": "TWO",
    "section": "A",
    "qNo": "1c",
    "unitId": "OS-U2",
    "topicId": "OS-U2-MUTEX",
    "subTopicId": "OS-U2-MUTEX-CS",
    "canonicalTopicName": "Mutual Exclusion",
    "canonicalSubTopicName": "Critical Section Problem",
    "questionType": "DEFINE",
    "hasDiagram": false,
    "difficulty": "EASY",
    "mappingStatus": "MAPPED",
    "mappingConfidence": "MEDIUM",
    "isRepeat": false,
    "repeatYears": []
  },
  {
    "subjectCode": "KCS401",
    "academicYear": "2022-23",
    "year": 2023,
    "examType": "EVEN_SEM",
    "rawText": "Define semaphore and its types.",
    "marks": 2,
    "markType": "TWO",
    "section": "A",
    "qNo": "1d",
    "unitId": "OS-U2",
    "topicId": "OS-U2-SEMAPHORE",
    "subTopicId": "OS-U2-SEMAPHORE-DEF",
    "canonicalTopicName": "Semaphores and Test Set",
    "canonicalSubTopicName": "Semaphores",
    "questionType": "DEFINE",
    "hasDiagram": false,
    "difficulty": "EASY",
    "mappingStatus": "MAPPED",
    "mappingConfidence": "HIGH",
    "isRepeat": true,
    "repeatYears": [2019, 2022]
  },
  {
    "subjectCode": "KCS401",
    "academicYear": "2022-23",
    "year": 2023,
    "examType": "EVEN_SEM",
    "rawText": "Explain starvation problem and its solution.",
    "marks": 2,
    "markType": "TWO",
    "section": "A",
    "qNo": "1e",
    "unitId": "OS-U3",
    "topicId": "OS-U3-SCHED",
    "subTopicId": "OS-U3-SCHED-ALGO",
    "canonicalTopicName": "CPU Scheduling",
    "canonicalSubTopicName": "Scheduling Algorithms",
    "questionType": "EXPLAIN",
    "hasDiagram": false,
    "difficulty": "EASY",
    "mappingStatus": "MAPPED",
    "mappingConfidence": "MEDIUM",
    "isRepeat": false,
    "repeatYears": []
  },
  {
    "subjectCode": "KCS401",
    "academicYear": "2022-23",
    "year": 2023,
    "examType": "EVEN_SEM",
    "rawText": "Explain internal and external fragmentation.",
    "marks": 2,
    "markType": "TWO",
    "section": "A",
    "qNo": "1f",
    "unitId": "OS-U4",
    "topicId": "OS-U4-BASIC",
    "subTopicId": "OS-U4-BASIC-VAR",
    "canonicalTopicName": "Basic Memory Management",
    "canonicalSubTopicName": "Variable Partition Multiprogramming",
    "questionType": "EXPLAIN",
    "hasDiagram": false,
    "difficulty": "EASY",
    "mappingStatus": "MAPPED",
    "mappingConfidence": "MEDIUM",
    "isRepeat": true,
    "repeatYears": [2018, 2019, 2022]
  },
  {
    "subjectCode": "KCS401",
    "academicYear": "2022-23",
    "year": 2023,
    "examType": "EVEN_SEM",
    "rawText": "Explain thrashing and locality of reference.",
    "marks": 2,
    "markType": "TWO",
    "section": "A",
    "qNo": "1g",
    "unitId": "OS-U4",
    "topicId": "OS-U4-VIRTUAL",
    "subTopicId": "OS-U4-VIRTUAL-THRASH",
    "canonicalTopicName": "Virtual Memory",
    "canonicalSubTopicName": "Thrashing",
    "questionType": "EXPLAIN",
    "hasDiagram": false,
    "difficulty": "EASY",
    "mappingStatus": "MAPPED",
    "mappingConfidence": "HIGH",
    "isRepeat": true,
    "repeatYears": [2019, 2022]
  },
  {
    "subjectCode": "KCS401",
    "academicYear": "2022-23",
    "year": 2023,
    "examType": "EVEN_SEM",
    "rawText": "Distinguish between physical and logical address space of a process.",
    "marks": 2,
    "markType": "TWO",
    "section": "A",
    "qNo": "1h",
    "unitId": "OS-U4",
    "topicId": "OS-U4-PAGING",
    "subTopicId": "OS-U4-PAGING-PAGE",
    "canonicalTopicName": "Paging and Segmentation",
    "canonicalSubTopicName": "Paging",
    "questionType": "COMPARE",
    "hasDiagram": false,
    "difficulty": "EASY",
    "mappingStatus": "MAPPED",
    "mappingConfidence": "HIGH",
    "isRepeat": true,
    "repeatYears": [2018, 2019, 2022]
  },
  {
    "subjectCode": "KCS401",
    "academicYear": "2022-23",
    "year": 2023,
    "examType": "EVEN_SEM",
    "rawText": "Explain various operations associated with a file.",
    "marks": 2,
    "markType": "TWO",
    "section": "A",
    "qNo": "1i",
    "unitId": "OS-U5",
    "topicId": "OS-U5-FILE",
    "subTopicId": "OS-U5-FILE-CONCEPT",
    "canonicalTopicName": "File System",
    "canonicalSubTopicName": "File Concept and Organization",
    "questionType": "EXPLAIN",
    "hasDiagram": false,
    "difficulty": "EASY",
    "mappingStatus": "MAPPED",
    "mappingConfidence": "HIGH",
    "isRepeat": true,
    "repeatYears": [2018, 2019]
  },
  {
    "subjectCode": "KCS401",
    "academicYear": "2022-23",
    "year": 2023,
    "examType": "EVEN_SEM",
    "rawText": "Explain tree level directory structure.",
    "marks": 2,
    "markType": "TWO",
    "section": "A",
    "qNo": "1j",
    "unitId": "OS-U5",
    "topicId": "OS-U5-FILE",
    "subTopicId": "OS-U5-FILE-DIR",
    "canonicalTopicName": "File System",
    "canonicalSubTopicName": "File Directories and Sharing",
    "questionType": "EXPLAIN",
    "hasDiagram": false,
    "difficulty": "EASY",
    "mappingStatus": "MAPPED",
    "mappingConfidence": "HIGH",
    "isRepeat": true,
    "repeatYears": [2018, 2019, 2022]
  },
  {
    "subjectCode": "KCS401",
    "academicYear": "2022-23",
    "year": 2023,
    "examType": "EVEN_SEM",
    "rawText": "Explain the following terms in detail: (i) Multiprocessor operating system (ii) Real time system (iii) Time sharing system",
    "marks": 10,
    "markType": "TEN",
    "section": "B",
    "qNo": "2a",
    "unitId": "OS-U1",
    "topicId": "OS-U1-CLASSIFY",
    "subTopicId": null,
    "canonicalTopicName": "Classification of Operating Systems",
    "canonicalSubTopicName": null,
    "questionType": "EXPLAIN",
    "hasDiagram": false,
    "difficulty": "MEDIUM",
    "mappingStatus": "MAPPED",
    "mappingConfidence": "HIGH",
    "isRepeat": true,
    "repeatYears": [2018, 2019, 2022]
  },
  {
    "subjectCode": "KCS401",
    "academicYear": "2022-23",
    "year": 2023,
    "examType": "EVEN_SEM",
    "rawText": "For the following processes, draw Gantt chart to illustrate the execution using (i) Preemptive priority scheduling (ii) Non-Preemptive priority scheduling. Also, Calculate average waiting time and average turnaround time. Process A(AT=0,BT=5,Pri=4), B(AT=2,BT=4,Pri=2), C(AT=2,BT=2,Pri=6), D(AT=4,BT=4,Pri=3). (Assumption: A larger priority number has higher priority.)",
    "marks": 10,
    "markType": "TEN",
    "section": "B",
    "qNo": "2b",
    "unitId": "OS-U3",
    "topicId": "OS-U3-SCHED",
    "subTopicId": "OS-U3-SCHED-ALGO",
    "canonicalTopicName": "CPU Scheduling",
    "canonicalSubTopicName": "Scheduling Algorithms",
    "questionType": "SOLVE",
    "hasDiagram": true,
    "difficulty": "HARD",
    "mappingStatus": "MAPPED",
    "mappingConfidence": "HIGH",
    "isRepeat": true,
    "repeatYears": [2018, 2019, 2022]
  },
  {
    "subjectCode": "KCS401",
    "academicYear": "2022-23",
    "year": 2023,
    "examType": "EVEN_SEM",
    "rawText": "Consider the given snapshot of a system with five processes (P0,P1,P2,P3,P4) and three resources (A,B,C). Allocation: P0(1,1,2), P1(2,1,2), P2(4,0,1), P3(0,2,0), P4(1,1,2). MAX: P0(4,3,3), P1(3,2,2), P2(9,0,2), P3(7,5,3), P4(11,2,3). Available: (2,1,0). (i) Calculate the content of Need Matrix. (ii) Apply safety algorithm and check the current system is in safe state or not. (iii) If the request from process P1 arrives for (1,1,0), can the request be granted immediately?",
    "marks": 10,
    "markType": "TEN",
    "section": "B",
    "qNo": "2c",
    "unitId": "OS-U3",
    "topicId": "OS-U3-DEADLOCK",
    "subTopicId": "OS-U3-DEADLOCK-PREV",
    "canonicalTopicName": "Deadlock",
    "canonicalSubTopicName": "Deadlock Prevention and Avoidance",
    "questionType": "SOLVE",
    "hasDiagram": false,
    "difficulty": "HARD",
    "mappingStatus": "MAPPED",
    "mappingConfidence": "HIGH",
    "isRepeat": true,
    "repeatYears": [2018, 2019, 2022]
  },
  {
    "subjectCode": "KCS401",
    "academicYear": "2022-23",
    "year": 2023,
    "examType": "EVEN_SEM",
    "rawText": "Define process and process control block. Also, describe process state transition diagram in detail.",
    "marks": 10,
    "markType": "TEN",
    "section": "B",
    "qNo": "2d",
    "unitId": "OS-U3",
    "topicId": "OS-U3-SCHED",
    "subTopicId": "OS-U3-SCHED-STATES",
    "canonicalTopicName": "CPU Scheduling",
    "canonicalSubTopicName": "Process States and PCB",
    "questionType": "DEFINE",
    "hasDiagram": true,
    "difficulty": "MEDIUM",
    "mappingStatus": "MAPPED",
    "mappingConfidence": "HIGH",
    "isRepeat": true,
    "repeatYears": [2018, 2019, 2022]
  },
  {
    "subjectCode": "KCS401",
    "academicYear": "2022-23",
    "year": 2023,
    "examType": "EVEN_SEM",
    "rawText": "Explain the concept of paging. Also, explain paging hardware support using TLB with suitable diagram.",
    "marks": 10,
    "markType": "TEN",
    "section": "B",
    "qNo": "2e",
    "unitId": "OS-U4",
    "topicId": "OS-U4-PAGING",
    "subTopicId": "OS-U4-PAGING-PAGE",
    "canonicalTopicName": "Paging and Segmentation",
    "canonicalSubTopicName": "Paging",
    "questionType": "EXPLAIN",
    "hasDiagram": true,
    "difficulty": "MEDIUM",
    "mappingStatus": "MAPPED",
    "mappingConfidence": "HIGH",
    "isRepeat": false,
    "repeatYears": []
  },
  {
    "subjectCode": "KCS401",
    "academicYear": "2022-23",
    "year": 2023,
    "examType": "EVEN_SEM",
    "rawText": "Explain the term RAID and its characteristics. Also, explain various RAID levels with their advantages and disadvantages.",
    "marks": 10,
    "markType": "TEN",
    "section": "C",
    "qNo": "3a",
    "unitId": "OS-U5",
    "topicId": "OS-U5-DISK",
    "subTopicId": "OS-U5-DISK-RAID",
    "canonicalTopicName": "Disk Scheduling",
    "canonicalSubTopicName": "RAID",
    "questionType": "EXPLAIN",
    "hasDiagram": false,
    "difficulty": "MEDIUM",
    "mappingStatus": "MAPPED",
    "mappingConfidence": "HIGH",
    "isRepeat": true,
    "repeatYears": [2019, 2022]
  },
  {
    "subjectCode": "KCS401",
    "academicYear": "2022-23",
    "year": 2023,
    "examType": "EVEN_SEM",
    "rawText": "Explain the concept of file system management. Also, explain various file allocation and file access mechanisms in details.",
    "marks": 10,
    "markType": "TEN",
    "section": "C",
    "qNo": "3b",
    "unitId": "OS-U5",
    "topicId": "OS-U5-FILE",
    "subTopicId": "OS-U5-FILE-IMPL",
    "canonicalTopicName": "File System",
    "canonicalSubTopicName": "File System Implementation",
    "questionType": "EXPLAIN",
    "hasDiagram": false,
    "difficulty": "MEDIUM",
    "mappingStatus": "MAPPED",
    "mappingConfidence": "HIGH",
    "isRepeat": true,
    "repeatYears": [2018, 2019, 2022]
  },
  {
    "subjectCode": "KCS401",
    "academicYear": "2022-23",
    "year": 2023,
    "examType": "EVEN_SEM",
    "rawText": "Explain producer consumer problem and its solution using semaphore.",
    "marks": 10,
    "markType": "TEN",
    "section": "C",
    "qNo": "4a",
    "unitId": "OS-U2",
    "topicId": "OS-U2-PROCESS",
    "subTopicId": "OS-U2-PROCESS-PRODCONS",
    "canonicalTopicName": "Process Concept and Concurrency",
    "canonicalSubTopicName": "Producer Consumer Problem",
    "questionType": "EXPLAIN",
    "hasDiagram": false,
    "difficulty": "MEDIUM",
    "mappingStatus": "MAPPED",
    "mappingConfidence": "HIGH",
    "isRepeat": false,
    "repeatYears": []
  },
  {
    "subjectCode": "KCS401",
    "academicYear": "2022-23",
    "year": 2023,
    "examType": "EVEN_SEM",
    "rawText": "Explain dinning philosopher problem and its solution using semaphore.",
    "marks": 10,
    "markType": "TEN",
    "section": "C",
    "qNo": "4b",
    "unitId": "OS-U2",
    "topicId": "OS-U2-CLASSICAL",
    "subTopicId": "OS-U2-CLASSICAL-DINING",
    "canonicalTopicName": "Classical Concurrency Problems",
    "canonicalSubTopicName": "Dining Philosopher Problem",
    "questionType": "EXPLAIN",
    "hasDiagram": false,
    "difficulty": "MEDIUM",
    "mappingStatus": "MAPPED",
    "mappingConfidence": "HIGH",
    "isRepeat": true,
    "repeatYears": [2019, 2022]
  },
  {
    "subjectCode": "KCS401",
    "academicYear": "2022-23",
    "year": 2023,
    "examType": "EVEN_SEM",
    "rawText": "Explain the concept of demand paging. Consider the given references to the following pages by a program: 0,9,0,1,8,1,8,7,8,7,1,2,8,2,7,8,2,3,8,3. How many pages faults will occur if the program has three-page frames available to it and uses: (i) FIFO replacement (ii) LRU replacement (iii) Optimal replacement.",
    "marks": 10,
    "markType": "TEN",
    "section": "C",
    "qNo": "5a",
    "unitId": "OS-U4",
    "topicId": "OS-U4-VIRTUAL",
    "subTopicId": "OS-U4-VIRTUAL-REPLACE",
    "canonicalTopicName": "Virtual Memory",
    "canonicalSubTopicName": "Page Replacement Algorithms",
    "questionType": "SOLVE",
    "hasDiagram": false,
    "difficulty": "HARD",
    "mappingStatus": "MAPPED",
    "mappingConfidence": "HIGH",
    "isRepeat": true,
    "repeatYears": [2018, 2019, 2022]
  },
  {
    "subjectCode": "KCS401",
    "academicYear": "2022-23",
    "year": 2023,
    "examType": "EVEN_SEM",
    "rawText": "Explain the terms hit ratio and miss ratio. On a simple paged system, associative registers hold the most active page entries and the full-page table is stored in main memory. If references satisfied by associative registers take 100ns, and references through main memory page table takes 180 ns, what must the hit ratio be to achieve an effective access time of 125 ns?",
    "marks": 10,
    "markType": "TEN",
    "section": "C",
    "qNo": "5b",
    "unitId": "OS-U4",
    "topicId": "OS-U4-PAGING",
    "subTopicId": "OS-U4-PAGING-PAGE",
    "canonicalTopicName": "Paging and Segmentation",
    "canonicalSubTopicName": "Paging",
    "questionType": "SOLVE",
    "hasDiagram": false,
    "difficulty": "HARD",
    "mappingStatus": "MAPPED",
    "mappingConfidence": "HIGH",
    "isRepeat": false,
    "repeatYears": []
  },
  {
    "subjectCode": "KCS401",
    "academicYear": "2022-23",
    "year": 2023,
    "examType": "EVEN_SEM",
    "rawText": "Explain the following terms: (i) Multilevel feedback Queue Scheduling (ii) Fixed portioning vs. variable partitioning.",
    "marks": 10,
    "markType": "TEN",
    "section": "C",
    "qNo": "6a",
    "unitId": "OS-U3",
    "topicId": "OS-U3-SCHED",
    "subTopicId": "OS-U3-SCHED-ALGO",
    "canonicalTopicName": "CPU Scheduling",
    "canonicalSubTopicName": "Scheduling Algorithms",
    "questionType": "EXPLAIN",
    "hasDiagram": false,
    "difficulty": "MEDIUM",
    "mappingStatus": "MAPPED",
    "mappingConfidence": "HIGH",
    "isRepeat": true,
    "repeatYears": [2018, 2019, 2022]
  },
  {
    "subjectCode": "KCS401",
    "academicYear": "2022-23",
    "year": 2023,
    "examType": "EVEN_SEM",
    "rawText": "Suppose the following disk request sequence (track numbers) for a disk with 100 tracks is given: 45, 20, 90, 10, 50, 60, 80, 25, 70. Assume that the initial position of the R/W head is on track 49. Calculate the net head movement using: (i) SSTF (ii) SCAN (iii) CSCAN (iv) LOOK.",
    "marks": 10,
    "markType": "TEN",
    "section": "C",
    "qNo": "6b",
    "unitId": "OS-U5",
    "topicId": "OS-U5-DISK",
    "subTopicId": "OS-U5-DISK-SCHED",
    "canonicalTopicName": "Disk Scheduling",
    "canonicalSubTopicName": "Disk Scheduling Algorithms",
    "questionType": "SOLVE",
    "hasDiagram": false,
    "difficulty": "HARD",
    "mappingStatus": "MAPPED",
    "mappingConfidence": "HIGH",
    "isRepeat": true,
    "repeatYears": [2019, 2022]
  },
  {
    "subjectCode": "KCS401",
    "academicYear": "2022-23",
    "year": 2023,
    "examType": "EVEN_SEM",
    "rawText": "Explain Deadlock and necessary conditions for deadlock. Also, Explain resource allocation graph with suitable diagram.",
    "marks": 10,
    "markType": "TEN",
    "section": "C",
    "qNo": "7a",
    "unitId": "OS-U3",
    "topicId": "OS-U3-DEADLOCK",
    "subTopicId": "OS-U3-DEADLOCK-CHAR",
    "canonicalTopicName": "Deadlock",
    "canonicalSubTopicName": "Deadlock Characterization",
    "questionType": "EXPLAIN",
    "hasDiagram": true,
    "difficulty": "MEDIUM",
    "mappingStatus": "MAPPED",
    "mappingConfidence": "HIGH",
    "isRepeat": true,
    "repeatYears": [2018, 2019, 2022]
  },
  {
    "subjectCode": "KCS401",
    "academicYear": "2022-23",
    "year": 2023,
    "examType": "EVEN_SEM",
    "rawText": "Explain the followings: (i) Buffering (ii) Polling (iii) Direct Memory Access (DMA).",
    "marks": 10,
    "markType": "TEN",
    "section": "C",
    "qNo": "7b",
    "unitId": "OS-U5",
    "topicId": "OS-U5-IO",
    "subTopicId": "OS-U5-IO-BUFFER",
    "canonicalTopicName": "I/O Management",
    "canonicalSubTopicName": "I/O Buffering",
    "questionType": "EXPLAIN",
    "hasDiagram": false,
    "difficulty": "MEDIUM",
    "mappingStatus": "MAPPED",
    "mappingConfidence": "HIGH",
    "isRepeat": true,
    "repeatYears": [2019, 2022]
  }
] 