{
  "subjectCode": "RCS403",
  "academicYear": "2017-18",
  "year": 2018,
  "examType": "EVEN_SEM",
  "questions": [
    {
      "rawText": "Define alphabet, string and language.",
      "marks": 2,
      "markType": "TWO",
      "section": "A",
      "qNo": "1a",
      "unitId": "TAFL-U1",
      "topicId": "TAFL-U1-INTRO",
      "subTopicId": "TAFL-U1-INTRO-BASIC",
      "canonicalTopicName": "Introduction to Theory of Computation",
      "canonicalSubTopicName": "Alphabet Symbol String Formal Languages",
      "questionType": "DEFINE",
      "hasDiagram": false,
      "difficulty": "EASY",
      "mappingStatus": "MAPPED",
      "mappingConfidence": "HIGH",
      "isRepeat": false,
      "repeatYears": []
    },
    {
      "rawText": "Design a regular expression that accepts all the strings for input alphabet {a,b} containing exactly 2 a's.",
      "marks": 2,
      "markType": "TWO",
      "section": "A",
      "qNo": "1b",
      "unitId": "TAFL-U2",
      "topicId": "TAFL-U2-REGEX",
      "subTopicId": null,
      "canonicalTopicName": "Regular Expressions",
      "canonicalSubTopicName": null,
      "questionType": "SOLVE",
      "hasDiagram": false,
      "difficulty": "EASY",
      "mappingStatus": "MAPPED",
      "mappingConfidence": "HIGH",
      "isRepeat": false,
      "repeatYears": []
    },
    {
      "rawText": "Design a NFA that accepts all the strings for input alphabet {a,b} containing the substring abba.",
      "marks": 2,
      "markType": "TWO",
      "section": "A",
      "qNo": "1c",
      "unitId": "TAFL-U1",
      "topicId": "TAFL-U1-NFA",
      "subTopicId": null,
      "canonicalTopicName": "Non Deterministic Finite Automaton",
      "canonicalSubTopicName": null,
      "questionType": "SOLVE",
      "hasDiagram": false,
      "difficulty": "EASY",
      "mappingStatus": "MAPPED",
      "mappingConfidence": "HIGH",
      "isRepeat": false,
      "repeatYears": []
    },
    {
      "rawText": "Define Chomsky hierarchy.",
      "marks": 2,
      "markType": "TWO",
      "section": "A",
      "qNo": "1d",
      "unitId": "TAFL-U3",
      "topicId": "TAFL-U3-CHOMSKYHIER",
      "subTopicId": null,
      "canonicalTopicName": "Chomsky Hierarchy",
      "canonicalSubTopicName": null,
      "questionType": "DEFINE",
      "hasDiagram": false,
      "difficulty": "EASY",
      "mappingStatus": "MAPPED",
      "mappingConfidence": "HIGH",
      "isRepeat": false,
      "repeatYears": []
    },
    {
      "rawText": "Is context free language closed under union? If yes, give an example.",
      "marks": 2,
      "markType": "TWO",
      "section": "A",
      "qNo": "1e",
      "unitId": "TAFL-U4",
      "topicId": "TAFL-U4-CFLPROPS",
      "subTopicId": "TAFL-U4-CFLPROPS-CLOSURE",
      "canonicalTopicName": "Properties of Context Free Languages",
      "canonicalSubTopicName": "Closure Properties of CFL",
      "questionType": "OTHER",
      "hasDiagram": false,
      "difficulty": "EASY",
      "mappingStatus": "MAPPED",
      "mappingConfidence": "HIGH",
      "isRepeat": false,
      "repeatYears": []
    },
    {
      "rawText": "Convert NFA into equivalent DFA by taking any suitable example.",
      "marks": 2,
      "markType": "TWO",
      "section": "A",
      "qNo": "1f",
      "unitId": "TAFL-U1",
      "topicId": "TAFL-U1-NFA",
      "subTopicId": "TAFL-U1-NFA-EQUIV",
      "canonicalTopicName": "Non Deterministic Finite Automaton",
      "canonicalSubTopicName": "Equivalence of DFA and NFA",
      "questionType": "SOLVE",
      "hasDiagram": false,
      "difficulty": "EASY",
      "mappingStatus": "MAPPED",
      "mappingConfidence": "HIGH",
      "isRepeat": false,
      "repeatYears": []
    },
    {
      "rawText": "Remove useless productions from the given productions: SAB|ab, AaA|B|a, BD|E",
      "marks": 2,
      "markType": "TWO",
      "section": "A",
      "qNo": "1g",
      "unitId": "TAFL-U3",
      "topicId": "TAFL-U3-SIMPLIFYCFG",
      "subTopicId": null,
      "canonicalTopicName": "Simplification of CFG",
      "canonicalSubTopicName": null,
      "questionType": "SOLVE",
      "hasDiagram": false,
      "difficulty": "EASY",
      "mappingStatus": "MAPPED",
      "mappingConfidence": "HIGH",
      "isRepeat": false,
      "repeatYears": []
    },
    {
      "rawText": "Define Deterministic Finite Automata (DFA) and design a DFA that accepts the binary number whose equivalent is divisible by 5.",
      "marks": 7,
      "markType": "SEVEN",
      "section": "B",
      "qNo": "2a",
      "unitId": "TAFL-U1",
      "topicId": "TAFL-U1-DFA",
      "subTopicId": "TAFL-U1-DFA-DEF",
      "canonicalTopicName": "Deterministic Finite Automaton",
      "canonicalSubTopicName": "DFA Definition and Representation",
      "questionType": "SOLVE",
      "hasDiagram": false,
      "difficulty": "HARD",
      "mappingStatus": "MAPPED",
      "mappingConfidence": "HIGH",
      "isRepeat": false,
      "repeatYears": []
    },
    {
      "rawText": "State recursive definition of regular expression and construct a regular expression corresponding to the state transition diagram as shown in Fig.1",
      "marks": 7,
      "markType": "SEVEN",
      "section": "B",
      "qNo": "2b",
      "unitId": "TAFL-U2",
      "topicId": "TAFL-U2-ARDEN",
      "subTopicId": "TAFL-U2-ARDEN-FA2RE",
      "canonicalTopicName": "Arden's Theorem",
      "canonicalSubTopicName": "FA to Regular Expression Conversion",
      "questionType": "DERIVE",
      "hasDiagram": true,
      "difficulty": "HARD",
      "mappingStatus": "MAPPED",
      "mappingConfidence": "HIGH",
      "isRepeat": false,
      "repeatYears": []
    },
    {
      "rawText": "Reduce the given grammar G=({S,A,B},{a,b},P,S) to Chomsky Normal Form. Where P is defined as: S→ bA | aB, A→ bAA | aS | a, B → aBB | bS | b",
      "marks": 7,
      "markType": "SEVEN",
      "section": "B",
      "qNo": "2c",
      "unitId": "TAFL-U3",
      "topicId": "TAFL-U3-NORMALFORMS",
      "subTopicId": "TAFL-U3-NORMALFORMS-CNF",
      "canonicalTopicName": "Normal Forms of CFG",
      "canonicalSubTopicName": "Chomsky Normal Form",
      "questionType": "SOLVE",
      "hasDiagram": false,
      "difficulty": "HARD",
      "mappingStatus": "MAPPED",
      "mappingConfidence": "HIGH",
      "isRepeat": false,
      "repeatYears": []
    },
    {
      "rawText": "What is Push Down Automata (PDA)? Design the PDA for the language L = {wcwR|w∈{a,b}*}",
      "marks": 7,
      "markType": "SEVEN",
      "section": "B",
      "qNo": "2d",
      "unitId": "TAFL-U4",
      "topicId": "TAFL-U4-NPDA",
      "subTopicId": "TAFL-U4-NPDA-DEF",
      "canonicalTopicName": "Nondeterministic Pushdown Automata",
      "canonicalSubTopicName": "NPDA Definition and Moves",
      "questionType": "SOLVE",
      "hasDiagram": false,
      "difficulty": "HARD",
      "mappingStatus": "MAPPED",
      "mappingConfidence": "HIGH",
      "isRepeat": false,
      "repeatYears": []
    },
    {
      "rawText": "Define Turing Machine (TM). Construct the TM for the language L = {anbn|n>0}.",
      "marks": 7,
      "markType": "SEVEN",
      "section": "B",
      "qNo": "2e",
      "unitId": "TAFL-U5",
      "topicId": "TAFL-U5-TMBASIC",
      "subTopicId": "TAFL-U5-TMBASIC-REPR",
      "canonicalTopicName": "Basic Turing Machine Model",
      "canonicalSubTopicName": "Representation of Turing Machines",
      "questionType": "SOLVE",
      "hasDiagram": false,
      "difficulty": "HARD",
      "mappingStatus": "MAPPED",
      "mappingConfidence": "HIGH",
      "isRepeat": false,
      "repeatYears": []
    },
    {
      "rawText": "Describe Mealy and Moore machines with example. Convert the given Mealy machine as shown in Fig. 2 into Moore Machine.",
      "marks": 7,
      "markType": "SEVEN",
      "section": "C",
      "qNo": "3a",
      "unitId": "TAFL-U1",
      "topicId": "TAFL-U1-FAOUTPUT",
      "subTopicId": "TAFL-U1-FAOUTPUT-EQUIV",
      "canonicalTopicName": "Finite Automata with Output",
      "canonicalSubTopicName": "Equivalence of Moore and Mealy",
      "questionType": "EXPLAIN",
      "hasDiagram": true,
      "difficulty": "MEDIUM",
      "mappingStatus": "MAPPED",
      "mappingConfidence": "HIGH",
      "isRepeat": false,
      "repeatYears": []
    },
    {
      "rawText": "Construct the minimum state automata equivalent to DFA described by Fig. 3",
      "marks": 7,
      "markType": "SEVEN",
      "section": "C",
      "qNo": "3b",
      "unitId": "TAFL-U1",
      "topicId": "TAFL-U1-MINIMIZATION",
      "subTopicId": null,
      "canonicalTopicName": "Minimization of Finite Automata",
      "canonicalSubTopicName": null,
      "questionType": "SOLVE",
      "hasDiagram": true,
      "difficulty": "HARD",
      "mappingStatus": "MAPPED",
      "mappingConfidence": "HIGH",
      "isRepeat": false,
      "repeatYears": []
    },
    {
      "rawText": "State Pumping Lemma for regular sets. Show that the set L={a^p | p is a prime} is not regular.",
      "marks": 7,
      "markType": "SEVEN",
      "section": "C",
      "qNo": "4a",
      "unitId": "TAFL-U2",
      "topicId": "TAFL-U2-PUMPING",
      "subTopicId": "TAFL-U2-PUMPING-APP",
      "canonicalTopicName": "Pumping Lemma for Regular Languages",
      "canonicalSubTopicName": "Application of Pumping Lemma",
      "questionType": "DERIVE",
      "hasDiagram": false,
      "difficulty": "HARD",
      "mappingStatus": "MAPPED",
      "mappingConfidence": "HIGH",
      "isRepeat": false,
      "repeatYears": []
    },
    {
      "rawText": "Discuss closure properties i.e. concatenation, union, intersection, complement of regular languages.",
      "marks": 7,
      "markType": "SEVEN",
      "section": "C",
      "qNo": "4b",
      "unitId": "TAFL-U2",
      "topicId": "TAFL-U2-CLOSURE",
      "subTopicId": null,
      "canonicalTopicName": "Closure Properties of Regular Languages",
      "canonicalSubTopicName": null,
      "questionType": "EXPLAIN",
      "hasDiagram": false,
      "difficulty": "MEDIUM",
      "mappingStatus": "MAPPED",
      "mappingConfidence": "HIGH",
      "isRepeat": false,
      "repeatYears": []
    },
    {
      "rawText": "Discuss inherent ambiguity of context free languages with suitable example. Construct the context free grammar that accepts language L={a^i b^j c^k | i = j or j = k; i, j, k are positive integers}.",
      "marks": 7,
      "markType": "SEVEN",
      "section": "C",
      "qNo": "5a",
      "unitId": "TAFL-U3",
      "topicId": "TAFL-U3-CFG",
      "subTopicId": "TAFL-U3-CFG-AMBIGUITY",
      "canonicalTopicName": "Context Free Grammar",
      "canonicalSubTopicName": "Ambiguity in CFG",
      "questionType": "EXPLAIN",
      "hasDiagram": false,
      "difficulty": "HARD",
      "mappingStatus": "MAPPED",
      "mappingConfidence": "HIGH",
      "isRepeat": false,
      "repeatYears": []
    },
    {
      "rawText": "Define parse tree. Find parse tree for the string abbcde considering the productions- S→aAcBe, A→Ab, A→b, B→d. Is this ambiguous? Justify.",
      "marks": 7,
      "markType": "SEVEN",
      "section": "C",
      "qNo": "5b",
      "unitId": "TAFL-U3",
      "topicId": "TAFL-U3-CFG",
      "subTopicId": "TAFL-U3-CFG-DERIV",
      "canonicalTopicName": "Context Free Grammar",
      "canonicalSubTopicName": "Derivations and Derivation Trees",
      "questionType": "SOLVE",
      "hasDiagram": false,
      "difficulty": "MEDIUM",
      "mappingStatus": "MAPPED",
      "mappingConfidence": "HIGH",
      "isRepeat": false,
      "repeatYears": []
    },
    {
      "rawText": "Differentiate between deterministic PDA (DPDA) and non-deterministic PDA (NPDA) with suitable example. Also discuss two stack PDA with example.",
      "marks": 7,
      "markType": "SEVEN",
      "section": "C",
      "qNo": "6a",
      "unitId": "TAFL-U4",
      "topicId": "TAFL-U4-DPDA",
      "subTopicId": "TAFL-U4-DPDA-DCFL",
      "canonicalTopicName": "Deterministic Pushdown Automata",
      "canonicalSubTopicName": "Deterministic Context Free Languages",
      "questionType": "COMPARE",
      "hasDiagram": false,
      "difficulty": "MEDIUM",
      "mappingStatus": "MAPPED",
      "mappingConfidence": "HIGH",
      "isRepeat": false,
      "repeatYears": []
    },
    {
      "rawText": "Construct a PDA equivalent to the following CFG productions: S→aAA, A→aS | bS | a",
      "marks": 7,
      "markType": "SEVEN",
      "section": "C",
      "qNo": "6b",
      "unitId": "TAFL-U4",
      "topicId": "TAFL-U4-PDACFL",
      "subTopicId": "TAFL-U4-PDACFL-PDA2CFG",
      "canonicalTopicName": "PDA and CFG Interconversion",
      "canonicalSubTopicName": "CFG for Pushdown Automata",
      "questionType": "SOLVE",
      "hasDiagram": false,
      "difficulty": "HARD",
      "mappingStatus": "MAPPED",
      "mappingConfidence": "HIGH",
      "isRepeat": false,
      "repeatYears": []
    },
    {
      "rawText": "Write short notes on the following: (i) Halting problem of Turing machine (ii) Recursive Language (iii) Variants of Turing Machine",
      "marks": 7,
      "markType": "SEVEN",
      "section": "C",
      "qNo": "7a",
      "unitId": "TAFL-U5",
      "topicId": "TAFL-U5-DECIDABILITY",
      "subTopicId": "TAFL-U5-DECIDABILITY-HALTING",
      "canonicalTopicName": "Recursive and RE Languages",
      "canonicalSubTopicName": "Halting Problem",
      "questionType": "OTHER",
      "hasDiagram": false,
      "difficulty": "MEDIUM",
      "mappingStatus": "MAPPED",
      "mappingConfidence": "HIGH",
      "isRepeat": false,
      "repeatYears": []
    },
    {
      "rawText": "Define Post's Correspondence Problem (PCP) and Modified PCP with its applications. Find any three PCP solutions of the lists x=(b,bab3,ba) and y=(b3,ba,a).",
      "marks": 7,
      "markType": "SEVEN",
      "section": "C",
      "qNo": "7b",
      "unitId": "TAFL-U5",
      "topicId": "TAFL-U5-DECIDABILITY",
      "subTopicId": "TAFL-U5-DECIDABILITY-PCP",
      "canonicalTopicName": "Recursive and RE Languages",
      "canonicalSubTopicName": "Post's Correspondence Problem",
      "questionType": "SOLVE",
      "hasDiagram": false,
      "difficulty": "HARD",
      "mappingStatus": "MAPPED",
      "mappingConfidence": "HIGH",
      "isRepeat": false,
      "repeatYears": []
    }
  ]
}